<?xml version="1.0" encoding="iso-8859-1"?>
<!DOCTYPE muclient>
<!-- Saved on Sunday, May 12, 2024, 12:36 PM -->
<!-- MuClient version 5.06 -->

<!-- Plugin "FA_KAIOKEN_DEATH" generated by Plugin Wizard -->

<muclient>
<plugin
   name="FA_KAIOKEN_DEATH"
   author="Fubar"
   id="365e3bd8262007ba58b5bec2"
   language="Lua"
   purpose="Plays sound when someone dies from kaioken."
   date_written="2024-05-12 12:34:23"
   requires="5.06"
   version="1.0"
   >
<description trim="y">
<![CDATA[
Plays "Another One Bites The Dust" from Queen. This activates when someone dies form using kaioken.
]]>
</description>

</plugin>


<!--  Get our standard constants -->

<include name="constants.lua"/>

<!--  Triggers  -->

<triggers>
  <trigger
   custom_colour="7"
   enabled="y"
   make_bold="y"
   make_underline="y"
   match="\[*\] [Fighter Adventure] *'s body went 'BOOM!' from over using Kaioken."
   sequence="100"
   sound="dust.wav"
  >
  </trigger>
</triggers>

<!--  Plugin help  -->

<aliases>
  <alias
   script="OnHelp"
   match="FA_KAIOKEN_DEATH:help"
   enabled="y"
  >
  </alias>
</aliases>

<script>
<![CDATA[
function OnHelp ()
  world.Note (world.GetPluginInfo (world.GetPluginID (), 3))
end
]]>
</script> 

</muclient>
